LICENSE
MANIFEST.in
ez_setup.py
setup.py
test_speed.py
PySpeed.egg-info/PKG-INFO
PySpeed.egg-info/SOURCES.txt
PySpeed.egg-info/dependency_links.txt
PySpeed.egg-info/requires.txt
PySpeed.egg-info/top_level.txt
speed/__init__.py
speed/base.py
speed/context.py
speed/gtk_widget.py