Metadata-Version: 1.0
Name: PySpeed
Version: 0.1.1
Summary: PySpeed - flexible progress bars for Python
Home-page: https://launchpad.net/pyspeed
Author: Amit Aronovitch
Author-email: pyspeed-dev@lists.launchpad.net
License: MIT/X11
Platform: any
